{
  "participants": [
    {
      "idCheval": "LOVE IS GOLD-KAZEERA-HAVANA GOLD",
      "pays": "France",
      "nom": "LOVE IS GOLD",
      "numPmu": 1,
      "age": 6,
      "sexe": "HONGRES",
      "race": "PUR-SANG",
      "statut": "PARTANT",
      "placeCorde": 8,
      "oeilleres": "SANS_OEILLERES",
      "proprietaire": "SARL GROUPE KR",
      "entraineur": "PIER.MENARD",
      "driver": "L.POGGIONOVO",
      "driverChange": false,
      "robe": {
        "code": "001",
        "libelleCourt": "ALEZAN",
        "libelleLong": "ALEZAN"
      },
      "indicateurInedit": false,
      "musique": "0p7p(25)5p3p1p5p3p1p5p",
      "nombreCourses": 32,
      "nombreVictoires": 5,
      "nombrePlaces": 17,
      "nombrePlacesSecond": 4,
      "nombrePlacesTroisieme": 3,
      "gainsParticipant": {
        "gainsCarriere": 11700700,
        "gainsVictoires": 6485000,
        "gainsPlace": 5215700,
        "gainsAnneeEnCours": 76300,
        "gainsAnneePrecedente": 4376400
      },
      "handicapValeur": 39,
      "nomPere": "HAVANA GOLD",
      "nomMere": "KAZEERA",
      "nomPereMere": "DUBAWI",
      "jumentPleine": false,
      "engagement": false,
      "supplement": 0,
      "handicapPoids": 630,
      "poidsConditionMonte": 615,
      "poidsConditionMonteChange": false,
      "dernierRapportDirect": {
        "typePari": "E_SIMPLE_GAGNANT",
        "rapport": 3.2,
        "typeRapport": "DIRECT",
        "nombreIndicateurTendance": 0,
        "dateRapport": 1775640995000,
        "permutation": 1,
        "favoris": true,
        "numPmu1": 1,
        "grossePrise": false
      },
      "dernierRapportReference": {
        "typePari": "E_SIMPLE_GAGNANT",
        "rapport": 2.9,
        "typeRapport": "REFERENCE",
        "nombreIndicateurTendance": 0,
        "dateRapport": 1775640600000,
        "permutation": 1,
        "favoris": true,
        "numPmu1": 1,
        "grossePrise": false
      },
      "urlCasaque": "https://www.pmu.fr/back-assets/hippique/casaques/08042026/R3/C2/P1.png",
      "eleveur": "ECURIE D'AUTHUIT",
      "paysEntrainement": "France",
      "allure": "GALOP"
    },
    {
      "idCheval": "DER SHTERN-MONGOLIA-AL WUKAIR",
      "pays": "France",
      "nom": "DER SHTERN",
      "numPmu": 2,
      "age": 4,
      "sexe": "HONGRES",
      "race": "PUR-SANG",
      "statut": "PARTANT",
      "placeCorde": 2,
      "oeilleres": "SANS_OEILLERES",
      "proprietaire": "MME B.HERMANGE/ECURIE R.E.",
      "entraineur": "G.FOURRIER",
      "driver": "Y.ROUSSET",
      "driverChange": false,
      "robe": {
        "code": "021",
        "libelleCourt": "BAI F.",
        "libelleLong": "BAI FONCE"
      },
      "indicateurInedit": false,
      "musique": "0p(25)0p2p3p6p6p1p",
      "nombreCourses": 7,
      "nombreVictoires": 1,
      "nombrePlaces": 4,
      "nombrePlacesSecond": 1,
      "nombrePlacesTroisieme": 1,
      "gainsParticipant": {
        "gainsCarriere": 930100,
        "gainsVictoires": 380000,
        "gainsPlace": 550100,
        "gainsAnneeEnCours": 0,
        "gainsAnneePrecedente": 930100
      },
      "handicapValeur": 34.5,
      "nomPere": "AL WUKAIR",
      "nomMere": "MONGOLIA",
      "nomPereMere": "MAXIOS",
      "jumentPleine": false,
      "engagement": true,
      "supplement": 1,
      "handicapPoids": 585,
      "poidsConditionMonteChange": false,
      "dernierRapportDirect": {
        "typePari": "E_SIMPLE_GAGNANT",
        "rapport": 17,
        "typeRapport": "DIRECT",
        "indicateurTendance": "-",
        "nombreIndicateurTendance": -1.65,
        "dateRapport": 1775640995000,
        "permutation": 1,
        "favoris": false,
        "numPmu1": 2,
        "grossePrise": false
      },
      "dernierRapportReference": {
        "typePari": "E_SIMPLE_GAGNANT",
        "rapport": 18,
        "typeRapport": "REFERENCE",
        "indicateurTendance": "+",
        "nombreIndicateurTendance": 0.55,
        "dateRapport": 1775640600000,
        "permutation": 1,
        "favoris": false,
        "numPmu1": 2,
        "grossePrise": false
      },
      "urlCasaque": "https://www.pmu.fr/back-assets/hippique/casaques/08042026/R3/C2/P2.png",
      "eleveur": "MME BRUNEHILDE HERMANGE",
      "paysEntrainement": "France",
      "allure": "GALOP"
    },
    {
      "idCheval": "TIMBER LIGHT-FOULOGNES-HUNTER'S LIGHT",
      "pays": "France",
      "nom": "TIMBER LIGHT",
      "numPmu": 3,
      "age": 5,
      "sexe": "HONGRES",
      "race": "PUR-SANG",
      "statut": "PARTANT",
      "placeCorde": 4,
      "oeilleres": "SANS_OEILLERES",
      "proprietaire": "MME B.DAHM",
      "entraineur": "MME B.DAHM",
      "driver": "A.BARON",
      "driverChange": false,
      "robe": {
        "code": "001",
        "libelleCourt": "ALEZAN",
        "libelleLong": "ALEZAN"
      },
      "indicateurInedit": false,
      "musique": "1p0p(25)9p5p7p9p0p(24)0p",
      "nombreCourses": 22,
      "nombreVictoires": 4,
      "nombrePlaces": 8,
      "nombrePlacesSecond": 2,
      "nombrePlacesTroisieme": 2,
      "gainsParticipant": {
        "gainsCarriere": 6735000,
        "gainsVictoires": 3900000,
        "gainsPlace": 2835000,
        "gainsAnneeEnCours": 400000,
        "gainsAnneePrecedente": 135000
      },
      "handicapValeur": 34,
      "nomPere": "HUNTER'S LIGHT",
      "nomMere": "FOULOGNES",
      "nomPereMere": "LOPE DE VEGA",
      "jumentPleine": false,
      "engagement": false,
      "supplement": 0,
      "handicapPoids": 580,
      "poidsConditionMonteChange": false,
      "dernierRapportDirect": {
        "typePari": "E_SIMPLE_GAGNANT",
        "rapport": 22,
        "typeRapport": "DIRECT",
        "indicateurTendance": "-",
        "nombreIndicateurTendance": -0.88,
        "dateRapport": 1775640995000,
        "permutation": 1,
        "favoris": false,
        "numPmu1": 3,
        "grossePrise": false
      },
      "dernierRapportReference": {
        "typePari": "E_SIMPLE_GAGNANT",
        "rapport": 23,
        "typeRapport": "REFERENCE",
        "indicateurTendance": "+",
        "nombreIndicateurTendance": 0.42,
        "dateRapport": 1775640600000,
        "permutation": 1,
        "favoris": false,
        "numPmu1": 3,
        "grossePrise": false
      },
      "urlCasaque": "https://www.pmu.fr/back-assets/hippique/casaques/08042026/R3/C2/P3.png",
      "eleveur": "MME YVETTE PANTALL",
      "paysEntrainement": "France",
      "allure": "GALOP"
    },
    {
      "idCheval": "ATANASIO-NAVIGATRICE-WHITECLIFFSOFDOVER",
      "pays": "France",
      "nom": "ATANASIO",
      "numPmu": 4,
      "age": 7,
      "sexe": "HONGRES",
      "race": "PUR-SANG",
      "statut": "PARTANT",
      "placeCorde": 3,
      "oeilleres": "SANS_OEILLERES",
      "proprietaire": "G.AUGUSTIN-NORMAND",
      "entraineur": "J.BOISNARD (S)",
      "driver": "H.LEBOUC",
      "driverChange": false,
      "robe": {
        "code": "020",
        "libelleCourt": "BAI",
        "libelleLong": "BAI"
      },
      "indicateurInedit": false,
      "musique": "4p(25)3p3p5p4p4p8p0p1p",
      "nombreCourses": 31,
      "nombreVictoires": 5,
      "nombrePlaces": 16,
      "nombrePlacesSecond": 2,
      "nombrePlacesTroisieme": 5,
      "gainsParticipant": {
        "gainsCarriere": 8002700,
        "gainsVictoires": 4600000,
        "gainsPlace": 3402700,
        "gainsAnneeEnCours": 233100,
        "gainsAnneePrecedente": 3614600
      },
      "handicapValeur": 33,
      "nomPere": "WHITECLIFFSOFDOVER",
      "nomMere": "NAVIGATRICE",
      "nomPereMere": "AUSSIE RULES",
      "jumentPleine": false,
      "engagement": true,
      "supplement": 1,
      "handicapPoids": 570,
      "poidsConditionMonteChange": false,
      "dernierRapportDirect": {
        "typePari": "E_SIMPLE_GAGNANT",
        "rapport": 4.8,
        "typeRapport": "DIRECT",
        "nombreIndicateurTendance": 0,
        "dateRapport": 1775640995000,
        "permutation": 1,
        "favoris": false,
        "numPmu1": 4,
        "grossePrise": false
      },
      "dernierRapportReference": {
        "typePari": "E_SIMPLE_GAGNANT",
        "rapport": 5.2,
        "typeRapport": "REFERENCE",
        "nombreIndicateurTendance": 0,
        "dateRapport": 1775640600000,
        "permutation": 1,
        "favoris": false,
        "numPmu1": 4,
        "grossePrise": false
      },
      "urlCasaque": "https://www.pmu.fr/back-assets/hippique/casaques/08042026/R3/C2/P4.png",
      "eleveur": "MR BRUNO MAZURE",
      "paysEntrainement": "France",
      "allure": "GALOP"
    },
    {
      "idCheval": "XCLUSIVITE-DOUBLE ET PAS-MADHMOON",
      "pays": "France",
      "nom": "XCLUSIVITE",
      "numPmu": 5,
      "age": 4,
      "sexe": "FEMELLES",
      "race": "PUR-SANG",
      "statut": "PARTANT",
      "placeCorde": 6,
      "oeilleres": "SANS_OEILLERES",
      "proprietaire": "F.HAYERES(S)/Y.BOTHAMY",
      "entraineur": "F.HAYERES (S)",
      "driver": "D.PROVOST",
      "driverChange": false,
      "robe": {
        "code": "020",
        "libelleCourt": "BAI",
        "libelleLong": "BAI"
      },
      "indicateurInedit": false,
      "musique": "1p(25)6p7p2p3p3p(24)4p",
      "nombreCourses": 7,
      "nombreVictoires": 1,
      "nombrePlaces": 4,
      "nombrePlacesSecond": 1,
      "nombrePlacesTroisieme": 2,
      "gainsParticipant": {
        "gainsCarriere": 1770000,
        "gainsVictoires": 595000,
        "gainsPlace": 1175000,
        "gainsAnneeEnCours": 595000,
        "gainsAnneePrecedente": 1050000
      },
      "handicapValeur": 32.5,
      "nomPere": "MADHMOON",
      "nomMere": "DOUBLE ET PAS",
      "nomPereMere": "ZAMINDAR",
      "jumentPleine": false,
      "engagement": false,
      "supplement": 0,
      "handicapPoids": 565,
      "poidsConditionMonteChange": false,
      "dernierRapportDirect": {
        "typePari": "E_SIMPLE_GAGNANT",
        "rapport": 7.4,
        "typeRapport": "DIRECT",
        "nombreIndicateurTendance": 0,
        "dateRapport": 1775640995000,
        "permutation": 1,
        "favoris": false,
        "numPmu1": 5,
        "grossePrise": false
      },
      "dernierRapportReference": {
        "typePari": "E_SIMPLE_GAGNANT",
        "rapport": 8.6,
        "typeRapport": "REFERENCE",
        "nombreIndicateurTendance": 0,
        "dateRapport": 1775640600000,
        "permutation": 1,
        "favoris": false,
        "numPmu1": 5,
        "grossePrise": false
      },
      "urlCasaque": "https://www.pmu.fr/back-assets/hippique/casaques/08042026/R3/C2/P5.png",
      "eleveur": "MME FREDERIQUE HAYERES",
      "paysEntrainement": "France",
      "allure": "GALOP"
    },
    {
      "idCheval": "MEAUTIS-MEDICAL KISS-SEA THE MOON",
      "pays": "France",
      "nom": "MEAUTIS",
      "numPmu": 6,
      "age": 5,
      "sexe": "HONGRES",
      "race": "PUR-SANG",
      "statut": "PARTANT",
      "placeCorde": 5,
      "oeilleres": "SANS_OEILLERES",
      "proprietaire": "G. AUGUSTIN-NORMAND/GENETS SRL",
      "entraineur": "A.BOTTI (S)",
      "driver": "M.GRANDIN",
      "driverChange": false,
      "robe": {
        "code": "001",
        "libelleCourt": "ALEZAN",
        "libelleLong": "ALEZAN"
      },
      "indicateurInedit": false,
      "musique": "2p0p3p(25)7p5p0p5p6p0p",
      "nombreCourses": 21,
      "nombreVictoires": 1,
      "nombrePlaces": 16,
      "nombrePlacesSecond": 4,
      "nombrePlacesTroisieme": 5,
      "gainsParticipant": {
        "gainsCarriere": 4900000,
        "gainsVictoires": 650000,
        "gainsPlace": 4250000,
        "gainsAnneeEnCours": 655200,
        "gainsAnneePrecedente": 939800
      },
      "handicapValeur": 32.5,
      "nomPere": "SEA THE MOON",
      "nomMere": "MEDICAL KISS",
      "nomPereMere": "MEDICEAN",
      "jumentPleine": false,
      "engagement": false,
      "supplement": 0,
      "handicapPoids": 565,
      "poidsConditionMonteChange": false,
      "dernierRapportDirect": {
        "typePari": "E_SIMPLE_GAGNANT",
        "rapport": 4.9,
        "typeRapport": "DIRECT",
        "nombreIndicateurTendance": 0,
        "dateRapport": 1775640995000,
        "permutation": 1,
        "favoris": false,
        "numPmu1": 6,
        "grossePrise": false
      },
      "dernierRapportReference": {
        "typePari": "E_SIMPLE_GAGNANT",
        "rapport": 5.1,
        "typeRapport": "REFERENCE",
        "nombreIndicateurTendance": 0,
        "dateRapport": 1775640600000,
        "permutation": 1,
        "favoris": false,
        "numPmu1": 6,
        "grossePrise": false
      },
      "urlCasaque": "https://www.pmu.fr/back-assets/hippique/casaques/08042026/R3/C2/P6.png",
      "eleveur": "SELECT BLOODSTOCK LTD",
      "paysEntrainement": "France",
      "allure": "GALOP"
    },
    {
      "idCheval": "WESTMINSTER PILOT-COSMOGYRAL-CRACKSMAN",
      "pays": "Royaume-Uni",
      "nom": "WESTMINSTER PILOT",
      "numPmu": 7,
      "age": 4,
      "sexe": "HONGRES",
      "race": "PUR-SANG",
      "statut": "PARTANT",
      "placeCorde": 9,
      "oeilleres": "SANS_OEILLERES",
      "proprietaire": "WESTMINSTER RACE HORSES S",
      "entraineur": "HA.PANTALL (S)",
      "driver": "M.PROTTI",
      "driverChange": false,
      "robe": {
        "code": "020",
        "libelleCourt": "BAI",
        "libelleLong": "BAI"
      },
      "indicateurInedit": false,
      "musique": "0p1p6p6p(25)3p",
      "nombreCourses": 5,
      "nombreVictoires": 1,
      "nombrePlaces": 3,
      "nombrePlacesSecond": 0,
      "nombrePlacesTroisieme": 1,
      "gainsParticipant": {
        "gainsCarriere": 760200,
        "gainsVictoires": 595000,
        "gainsPlace": 165200,
        "gainsAnneeEnCours": 718500,
        "gainsAnneePrecedente": 41700
      },
      "handicapValeur": 32,
      "nomPere": "CRACKSMAN",
      "nomMere": "COSMOGYRAL",
      "nomPereMere": "CAMELOT",
      "jumentPleine": false,
      "engagement": false,
      "supplement": 0,
      "handicapPoids": 560,
      "poidsConditionMonte": 545,
      "poidsConditionMonteChange": false,
      "dernierRapportDirect": {
        "typePari": "E_SIMPLE_GAGNANT",
        "rapport": 17,
        "typeRapport": "DIRECT",
        "indicateurTendance": "-",
        "nombreIndicateurTendance": -1.67,
        "dateRapport": 1775640995000,
        "permutation": 1,
        "favoris": false,
        "numPmu1": 7,
        "grossePrise": false
      },
      "dernierRapportReference": {
        "typePari": "E_SIMPLE_GAGNANT",
        "rapport": 16,
        "typeRapport": "REFERENCE",
        "indicateurTendance": "-",
        "nombreIndicateurTendance": -1.23,
        "dateRapport": 1775640600000,
        "permutation": 1,
        "favoris": false,
        "numPmu1": 7,
        "grossePrise": false
      },
      "urlCasaque": "https://www.pmu.fr/back-assets/hippique/casaques/08042026/R3/C2/P7.png",
      "eleveur": "KINGWOOD STUD LTD",
      "paysEntrainement": "France",
      "allure": "GALOP"
    },
    {
      "idCheval": "ONE EYE JACK-RIVEN STAR-STARSPANGLEDBANNER",
      "pays": "Irlande",
      "nom": "ONE EYE JACK",
      "numPmu": 8,
      "age": 4,
      "sexe": "HONGRES",
      "race": "PUR-SANG",
      "statut": "PARTANT",
      "placeCorde": 7,
      "oeilleres": "SANS_OEILLERES",
      "proprietaire": "SC THIERRY PIGEON",
      "entraineur": "FR.MONFORT (S)",
      "driver": "J.GUILLOCHON",
      "driverChange": false,
      "robe": {
        "code": "020",
        "libelleCourt": "BAI",
        "libelleLong": "BAI"
      },
      "indicateurInedit": false,
      "musique": "7p6p(25)7p8p6p9p5p(24)6p",
      "nombreCourses": 10,
      "nombreVictoires": 1,
      "nombrePlaces": 3,
      "nombrePlacesSecond": 0,
      "nombrePlacesTroisieme": 0,
      "gainsParticipant": {
        "gainsCarriere": 800200,
        "gainsVictoires": 621300,
        "gainsPlace": 178900,
        "gainsAnneeEnCours": 58900,
        "gainsAnneePrecedente": 120000
      },
      "handicapValeur": 32,
      "nomPere": "STARSPANGLEDBANNER",
      "nomMere": "RIVEN STAR",
      "nomPereMere": "FALCO",
      "jumentPleine": false,
      "engagement": false,
      "supplement": 0,
      "handicapPoids": 560,
      "poidsConditionMonteChange": false,
      "dernierRapportDirect": {
        "typePari": "E_SIMPLE_GAGNANT",
        "rapport": 31,
        "typeRapport": "DIRECT",
        "indicateurTendance": "-",
        "nombreIndicateurTendance": -1.26,
        "dateRapport": 1775640995000,
        "permutation": 1,
        "favoris": false,
        "numPmu1": 8,
        "grossePrise": false
      },
      "dernierRapportReference": {
        "typePari": "E_SIMPLE_GAGNANT",
        "rapport": 27,
        "typeRapport": "REFERENCE",
        "indicateurTendance": "+",
        "nombreIndicateurTendance": 0.35,
        "dateRapport": 1775640600000,
        "permutation": 1,
        "favoris": false,
        "numPmu1": 8,
        "grossePrise": false
      },
      "urlCasaque": "https://www.pmu.fr/back-assets/hippique/casaques/08042026/R3/C2/P8.png",
      "eleveur": "ECURIE SKYMARC FARM",
      "paysEntrainement": "France",
      "allure": "GALOP"
    },
    {
      "idCheval": "KALAFA-KALAHANA-DARIYAN",
      "pays": "France",
      "nom": "KALAFA",
      "numPmu": 9,
      "age": 4,
      "sexe": "FEMELLES",
      "race": "PUR-SANG",
      "statut": "PARTANT",
      "placeCorde": 1,
      "oeilleres": "SANS_OEILLERES",
      "proprietaire": "ECURIE TRIDENT RACING",
      "entraineur": "L.GADBIN (S)",
      "driver": "C.GROSBOIS",
      "driverChange": false,
      "robe": {
        "code": "001",
        "libelleCourt": "ALEZAN",
        "libelleLong": "ALEZAN"
      },
      "indicateurInedit": false,
      "musique": "0p(25)0p2p2p1p3p5p5p",
      "nombreCourses": 9,
      "nombreVictoires": 1,
      "nombrePlaces": 5,
      "nombrePlacesSecond": 2,
      "nombrePlacesTroisieme": 1,
      "gainsParticipant": {
        "gainsCarriere": 2693600,
        "gainsVictoires": 1345000,
        "gainsPlace": 1348600,
        "gainsAnneeEnCours": 0,
        "gainsAnneePrecedente": 2693600
      },
      "handicapValeur": 31,
      "nomPere": "DARIYAN",
      "nomMere": "KALAHANA",
      "nomPereMere": "DAWN APPROACH",
      "jumentPleine": false,
      "engagement": false,
      "supplement": 0,
      "handicapPoids": 550,
      "poidsConditionMonteChange": false,
      "dernierRapportDirect": {
        "typePari": "E_SIMPLE_GAGNANT",
        "rapport": 15,
        "typeRapport": "DIRECT",
        "indicateurTendance": "-",
        "nombreIndicateurTendance": -0.62,
        "dateRapport": 1775640995000,
        "permutation": 1,
        "favoris": false,
        "numPmu1": 9,
        "grossePrise": false
      },
      "dernierRapportReference": {
        "typePari": "E_SIMPLE_GAGNANT",
        "rapport": 16,
        "typeRapport": "REFERENCE",
        "indicateurTendance": "-",
        "nombreIndicateurTendance": -0.6,
        "dateRapport": 1775640600000,
        "permutation": 1,
        "favoris": false,
        "numPmu1": 9,
        "grossePrise": false
      },
      "urlCasaque": "https://www.pmu.fr/back-assets/hippique/casaques/08042026/R3/C2/P9.png",
      "eleveur": "AGA KHAN STUDS SC",
      "paysEntrainement": "France",
      "allure": "GALOP"
    },
    {
      "idCheval": "MAESTRAL-ZAMIRA-STORM THE STARS",
      "pays": "France",
      "nom": "MAESTRAL",
      "numPmu": 10,
      "age": 4,
      "sexe": "HONGRES",
      "race": "PUR-SANG",
      "statut": "PARTANT",
      "placeCorde": 10,
      "oeilleres": "OEILLERES_AUSTRALIENNES",
      "proprietaire": "FW.GEFFRIAUD",
      "entraineur": "MME S.GEFFRIAUD",
      "driver": "L.DAVID",
      "driverChange": false,
      "robe": {
        "code": "020",
        "libelleCourt": "BAI",
        "libelleLong": "BAI"
      },
      "indicateurInedit": false,
      "musique": "0p8p(25)1p0p4p3p6p2p8p",
      "nombreCourses": 14,
      "nombreVictoires": 1,
      "nombrePlaces": 6,
      "nombrePlacesSecond": 1,
      "nombrePlacesTroisieme": 1,
      "gainsParticipant": {
        "gainsCarriere": 1507900,
        "gainsVictoires": 815000,
        "gainsPlace": 692900,
        "gainsAnneeEnCours": 0,
        "gainsAnneePrecedente": 1507900
      },
      "handicapValeur": 27.5,
      "nomPere": "STORM THE STARS",
      "nomMere": "ZAMIRA",
      "nomPereMere": "POET'S VOICE",
      "jumentPleine": false,
      "engagement": false,
      "supplement": 0,
      "handicapPoids": 515,
      "poidsConditionMonte": 490,
      "poidsConditionMonteChange": false,
      "dernierRapportDirect": {
        "typePari": "E_SIMPLE_GAGNANT",
        "rapport": 31,
        "typeRapport": "DIRECT",
        "indicateurTendance": "-",
        "nombreIndicateurTendance": -3.62,
        "dateRapport": 1775640995000,
        "permutation": 1,
        "favoris": false,
        "numPmu1": 10,
        "grossePrise": false
      },
      "dernierRapportReference": {
        "typePari": "E_SIMPLE_GAGNANT",
        "rapport": 27,
        "typeRapport": "REFERENCE",
        "indicateurTendance": "+",
        "nombreIndicateurTendance": 0.35,
        "dateRapport": 1775640600000,
        "permutation": 1,
        "favoris": false,
        "numPmu1": 10,
        "grossePrise": false
      },
      "urlCasaque": "https://www.pmu.fr/back-assets/hippique/casaques/08042026/R3/C2/P10.png",
      "eleveur": "MR JEAN-MICHEL APPRIOU",
      "paysEntrainement": "France",
      "allure": "GALOP"
    }
  ],
  "ecuries": [],
  "spriteCasaques": [
    {
      "heightSize": 19,
      "url": "https://www.pmu.fr/back-assets/hippique/casaques/08042026/R3/C2/sprite_casaques_19px_size.png",
      "originalSize": false
    },
    {
      "heightSize": 40,
      "url": "https://www.pmu.fr/back-assets/hippique/casaques/08042026/R3/C2/sprite_casaques_40px_size.png",
      "originalSize": false
    },
    {
      "heightSize": 261,
      "url": "https://www.pmu.fr/back-assets/hippique/casaques/08042026/R3/C2/sprite_casaques_original_size.png",
      "originalSize": true
    }
  ],
  "cached": false
}